casechange/__init__.py
casechange/__main__.py
casechange_wic-1.0.4.dist-info/entry_points.txt
casechange_wic-1.0.4.dist-info/licenses/LICENSE
casechange_wic-1.0.4.dist-info/WHEEL
casechange_wic-1.0.4.dist-info/METADATA
casechange_wic-1.0.4.dist-info/RECORD
