Metadata-Version: 2.4
Name: casechange_wic
Version: 1.0.4
Summary: Case Change
Author-email: Anuradha <anuradhawick@gmail.com>
License-Expression: MIT
License-File: LICENSE
Project-URL: Home, https://github.com/anuradhawick/casechange
